gthnk/__init__.py
gthnk/__meta__.py
gthnk/cli.py
gthnk/syntax.py
gthnk/utils.py
gthnk/.mypy_cache/.gitignore
gthnk/.mypy_cache/CACHEDIR.TAG
gthnk/.mypy_cache/3.10/@plugins_snapshot.json
gthnk/.mypy_cache/3.10/__future__.data.json
gthnk/.mypy_cache/3.10/__future__.meta.json
gthnk/.mypy_cache/3.10/__main__.data.json
gthnk/.mypy_cache/3.10/__main__.meta.json
gthnk/.mypy_cache/3.10/_ast.data.json
gthnk/.mypy_cache/3.10/_ast.meta.json
gthnk/.mypy_cache/3.10/_bisect.data.json
gthnk/.mypy_cache/3.10/_bisect.meta.json
gthnk/.mypy_cache/3.10/_codecs.data.json
gthnk/.mypy_cache/3.10/_codecs.meta.json
gthnk/.mypy_cache/3.10/_collections_abc.data.json
gthnk/.mypy_cache/3.10/_collections_abc.meta.json
gthnk/.mypy_cache/3.10/_compression.data.json
gthnk/.mypy_cache/3.10/_compression.meta.json
gthnk/.mypy_cache/3.10/_ctypes.data.json
gthnk/.mypy_cache/3.10/_ctypes.meta.json
gthnk/.mypy_cache/3.10/_decimal.data.json
gthnk/.mypy_cache/3.10/_decimal.meta.json
gthnk/.mypy_cache/3.10/_operator.data.json
gthnk/.mypy_cache/3.10/_operator.meta.json
gthnk/.mypy_cache/3.10/_random.data.json
gthnk/.mypy_cache/3.10/_random.meta.json
gthnk/.mypy_cache/3.10/_socket.data.json
gthnk/.mypy_cache/3.10/_socket.meta.json
gthnk/.mypy_cache/3.10/_thread.data.json
gthnk/.mypy_cache/3.10/_thread.meta.json
gthnk/.mypy_cache/3.10/_warnings.data.json
gthnk/.mypy_cache/3.10/_warnings.meta.json
gthnk/.mypy_cache/3.10/_weakref.data.json
gthnk/.mypy_cache/3.10/_weakref.meta.json
gthnk/.mypy_cache/3.10/_weakrefset.data.json
gthnk/.mypy_cache/3.10/_weakrefset.meta.json
gthnk/.mypy_cache/3.10/abc.data.json
gthnk/.mypy_cache/3.10/abc.meta.json
gthnk/.mypy_cache/3.10/argparse.data.json
gthnk/.mypy_cache/3.10/argparse.meta.json
gthnk/.mypy_cache/3.10/array.data.json
gthnk/.mypy_cache/3.10/array.meta.json
gthnk/.mypy_cache/3.10/ast.data.json
gthnk/.mypy_cache/3.10/ast.meta.json
gthnk/.mypy_cache/3.10/atexit.data.json
gthnk/.mypy_cache/3.10/atexit.meta.json
gthnk/.mypy_cache/3.10/base64.data.json
gthnk-0.8.1.dist-info/METADATA
gthnk-0.8.1.dist-info/WHEEL
gthnk-0.8.1.dist-info/top_level.txt
gthnk-0.8.1.dist-info/RECORD
