Metadata-Version: 2.1
Name: gthnk
Version: 0.8.1
Summary: gthnk is a personal knowledge management system
Home-page: http://www.gthnk.com
Author: Ian Dennis Miller
Author-email: ian@iandennismiller.com
License: MIT
Classifier: Development Status :: 4 - Beta
Classifier: Framework :: Flask
Classifier: Intended Audience :: End Users/Desktop
Classifier: Intended Audience :: Developers
Classifier: License :: OSI Approved :: MIT License
Classifier: Operating System :: MacOS :: MacOS X
Classifier: Programming Language :: Python :: 3.8
Classifier: Topic :: Database :: Front-Ends
Requires-Dist: python-dotenv
Requires-Dist: rich
Requires-Dist: trogon
Provides-Extra: dev
Requires-Dist: pytest ; extra == 'dev'
Requires-Dist: pdbpp ; extra == 'dev'
Requires-Dist: pylint ; extra == 'dev'
Requires-Dist: rstcheck ; extra == 'dev'
Requires-Dist: mypy ; extra == 'dev'
Requires-Dist: pytest-cov ; extra == 'dev'
Requires-Dist: Flask-Testing ; extra == 'dev'
Requires-Dist: twine ; extra == 'dev'
Provides-Extra: server
Requires-Dist: jinja2 (<3.1.0) ; extra == 'server'
Requires-Dist: flask (==1.1.2) ; extra == 'server'
Requires-Dist: werkzeug (==2.0.3) ; extra == 'server'
Requires-Dist: Markdown (<3.2) ; extra == 'server'
Requires-Dist: itsdangerous (==2.0.1) ; extra == 'server'
Requires-Dist: Flask-WTF ; extra == 'server'
Requires-Dist: flask-markdown ; extra == 'server'
Requires-Dist: mdx-linkify (==1.0) ; extra == 'server'
Requires-Dist: mdx-journal (>=0.1.4) ; extra == 'server'
